sat_templates/VERSION
sat_templates/__init__.py
sat_templates/i18n/babel.ini
sat_templates/i18n/fr.po
sat_templates/i18n/sat.pot
sat_templates/i18n/sk.po
sat_templates/i18n/fr/LC_MESSAGES/sat.mo
sat_templates/i18n/sk/LC_MESSAGES/sat.mo
sat_templates/templates/default/app/app.html
sat_templates/templates/default/base/base.html
sat_templates/templates/default/blog/articles.html
sat_templates/templates/default/blog/atom.xml
sat_templates/templates/default/blog/discover.html
sat_templates/templates/default/blog/item.html
sat_templates/templates/default/blog/macros.html
sat_templates/templates/default/chat/chat.html
sat_templates/templates/default/chat/message.html
sat_templates/templates/default/chat/select.html
sat_templates/templates/default/components/avatar.html
sat_templates/templates/default/components/block.html
sat_templates/templates/default/components/common.html
sat_templates/templates/default/components/images.html
sat_templates/templates/default/components/menu_labels.html
sat_templates/templates/default/error/401.html
sat_templates/templates/default/error/403.html
sat_templates/templates/default/error/404.html
sat_templates/templates/default/error/base.html
sat_templates/templates/default/event/admin.html
sat_templates/templates/default/event/attendance.html
sat_templates/templates/default/event/counter.html
sat_templates/templates/default/event/create.html
sat_templates/templates/default/event/invitation.html
sat_templates/templates/default/event/overview.html
sat_templates/templates/default/file/discover.html
sat_templates/templates/default/file/overview.html
sat_templates/templates/default/forum/overview.html
sat_templates/templates/default/forum/view.html
sat_templates/templates/default/forum/view_topics.html
sat_templates/templates/default/input/field.html
sat_templates/templates/default/input/form.html
sat_templates/templates/default/input/navigation.html
sat_templates/templates/default/input/textbox.html
sat_templates-0.7.0.dist-info/COPYING
sat_templates-0.7.0.dist-info/METADATA
sat_templates-0.7.0.dist-info/WHEEL
sat_templates-0.7.0.dist-info/top_level.txt
sat_templates-0.7.0.dist-info/RECORD
