Metadata-Version: 2.1
Name: sat-templates
Version: 0.7.0
Summary: Templates for Salut à Toi XMPP client
Home-page: https://salut-a-toi.org
Author: Association « Salut à Toi »
Author-email: contact@salut-a-toi.org
License: UNKNOWN
Platform: UNKNOWN
Classifier: Development Status :: 3 - Alpha
Classifier: Programming Language :: Python :: 2.7
Classifier: Programming Language :: Python :: 2 :: Only
Classifier: License :: OSI Approved :: GNU Affero General Public License v3 or later (AGPLv3+)
